
	{
		"ids":[
			{
				"id": "motivoatencionadminpendientes-results",
				"headers": [
				{ "label": "Tipo Motivo" },
				{ "label": "Motivo" }
				],
				"rows": [
					{
						"id": "1",
						"data": [
							"Rechazo",
							"Eveniet qui sed dolores ut aspernatur. Ut quis commodi ipsam laudantium dolorem deserunt perspiciatis. Aut autem voluptatem ipsa."
						]
					},
					{
						"id": "2",
						"data": [
							"Rechazo",
							"Aut velit sunt voluptatibus excepturi dicta velit consequatur. Unde doloremque modi vel. Saepe cum accusamus rerum corrupti magnam. Nihil id assumenda illo. In dignissimos est."
						]
					},
					{
						"id": "3",
						"data": [
							"Rechazo",
							"Voluptatum rerum accusamus est velit accusamus atque eos. Explicabo labore rerum nulla libero. Aut ipsa aut assumenda id ducimus."
						]
					},
					{
						"id": "4",
						"data": [
							"Rechazo",
							"A magni ab. Distinctio soluta in voluptatum doloremque at. Ea eius sit sint alias deserunt quaerat tempore. Dolore ratione est tempore."
						]
					},
					{
						"id": "5",
						"data": [
							"Rechazo",
							"Voluptates corrupti aut temporibus quo voluptatem excepturi. Assumenda numquam eaque et modi totam mollitia. Eligendi numquam odio soluta eaque porro voluptas rem. Voluptates veritatis consequatur tempora magnam. Rerum aut beatae quis perferendis dicta."
						]
					},
					{
						"id": "6",
						"data": [
							"Rechazo",
							"Et rerum ex. Et dolor sint blanditiis odio. Eum beatae quia aut autem commodi. Et non quam laudantium. Quod reiciendis ipsa officia non."
						]
					},
					{
						"id": "7",
						"data": [
							"Rechazo",
							"Qui porro enim quis odit. Sequi reprehenderit eaque necessitatibus ipsam vel sunt. Minus aperiam eius. Sed ut nesciunt ea necessitatibus qui debitis."
						]
					},
					{
						"id": "8",
						"data": [
							"Rechazo",
							"Nulla cum qui quia. Aliquam rerum cum ut. Modi dolor eaque quam id a molestiae ad. Iusto ab animi explicabo rerum. Voluptatum exercitationem blanditiis optio nulla."
						]
					},
					{
						"id": "9",
						"data": [
							"Rechazo",
							"Id consectetur qui. Voluptas eum corrupti. Impedit ipsum laudantium quaerat. Commodi et quo illum assumenda pariatur pariatur similique."
						]
					},
					{
						"id": "10",
						"data": [
							"Rechazo",
							"Odit necessitatibus adipisci in et incidunt soluta. Modi corporis doloribus repellat iusto adipisci. Dolor eos veritatis consequuntur consectetur sed sed repudiandae."
						]
					}
				]
			}
		]
	}
